trytond/modules/health_crypto/COPYING
trytond/modules/health_crypto/README.rst
trytond/modules/health_crypto/__init__.py
trytond/modules/health_crypto/health_crypto.py
trytond/modules/health_crypto/health_crypto_view.xml
trytond/modules/health_crypto/locale/ar.po
trytond/modules/health_crypto/locale/de.po
trytond/modules/health_crypto/locale/el.po
trytond/modules/health_crypto/locale/eo.po
trytond/modules/health_crypto/locale/es.po
trytond/modules/health_crypto/locale/fr.po
trytond/modules/health_crypto/locale/health_crypto.pot
trytond/modules/health_crypto/locale/it_IT.po
trytond/modules/health_crypto/locale/ja_JP.po
trytond/modules/health_crypto/locale/ka.po
trytond/modules/health_crypto/locale/lo.po
trytond/modules/health_crypto/locale/pt_BR.po
trytond/modules/health_crypto/locale/sv.po
trytond/modules/health_crypto/locale/tr.po
trytond/modules/health_crypto/locale/uk.po
trytond/modules/health_crypto/locale/zh_CN.po
trytond/modules/health_crypto/pyproject.toml
trytond/modules/health_crypto/tests/__init__.py
trytond/modules/health_crypto/tests/test_health_crypto.py
trytond/modules/health_crypto/tryton.cfg
trytond/modules/health_crypto/view/gnuhealth_birth_certificate_form.xml
trytond/modules/health_crypto/view/gnuhealth_death_certificate_form.xml
trytond/modules/health_crypto/view/gnuhealth_patient_evaluation_form.xml
trytond/modules/health_crypto/view/prescription_form.xml
gnuhealth_crypto-5.0.2.dist-info/METADATA
gnuhealth_crypto-5.0.2.dist-info/WHEEL
gnuhealth_crypto-5.0.2.dist-info/licenses/COPYING
gnuhealth_crypto-5.0.2.dist-info/RECORD
